it/__init__.py
it/base.py
it/core.py
pennywise-0.0.11.data/scripts/pennywise
pennywise-0.0.11.dist-info/LICENSE
pennywise-0.0.11.dist-info/METADATA
pennywise-0.0.11.dist-info/WHEEL
pennywise-0.0.11.dist-info/top_level.txt
pennywise-0.0.11.dist-info/RECORD
